context/__init__.py
context/chunking.py
context/client.py
context/config.py
context/filesystem.py
context-0.1.0.dist-info/LICENSE
context-0.1.0.dist-info/METADATA
context-0.1.0.dist-info/WHEEL
context-0.1.0.dist-info/top_level.txt
context-0.1.0.dist-info/RECORD
