Metadata-Version: 2.1
Name: context
Version: 0.1.0
Summary: A filesystem-like interface for ChromaDB with semantic search
Author: Jeff
License: MIT
Project-URL: Homepage, https://github.com/yourusername/context
Project-URL: Repository, https://github.com/yourusername/context
Project-URL: Documentation, https://github.com/yourusername/context#readme
Project-URL: Issues, https://github.com/yourusername/context/issues
Keywords: chromadb,vector-database,filesystem,semantic-search,embeddings,rag,llm
Classifier: Development Status :: 4 - Beta
Classifier: Intended Audience :: Developers
Classifier: License :: OSI Approved :: MIT License
Classifier: Operating System :: OS Independent
Classifier: Programming Language :: Python :: 3
Classifier: Programming Language :: Python :: 3.8
Classifier: Programming Language :: Python :: 3.9
Classifier: Programming Language :: Python :: 3.10
Classifier: Programming Language :: Python :: 3.11
Classifier: Programming Language :: Python :: 3.12
Classifier: Programming Language :: Python :: 3.13
Classifier: Topic :: Database
Classifier: Topic :: System :: Filesystems
Classifier: Topic :: Scientific/Engineering :: Artificial Intelligence
Classifier: Typing :: Typed
Requires-Python: >=3.8
License-File: LICENSE
Provides-Extra: all
Requires-Dist: tomli>=2.0; python_version < "3.11" and extra == "all"
Provides-Extra: dev
Requires-Dist: pytest>=7.0; extra == "dev"
Requires-Dist: pytest-cov>=4.0; extra == "dev"
Requires-Dist: mypy>=1.0; extra == "dev"
Requires-Dist: ruff>=0.1.0; extra == "dev"
Provides-Extra: toml
Requires-Dist: tomli>=2.0; python_version < "3.11" and extra == "toml"
